{
  "packlistId": 1181939,
  "error": "Impresora no disponible: B4005029",
  "stack": "Error: Impresora no disponible: B4005029\n    at PacklistScheduler.sendToPrint (C:\\Users\\Administrador.LOAD\\Desktop\\apidoc\\Apidoc\\src\\jobs\\packlistScheduler.js:634:13)\n    at process.processTicksAndRejections (node:internal/process/task_queues:95:5)\n    at async PacklistScheduler.processSinglePacklist (C:\\Users\\Administrador.LOAD\\Desktop\\apidoc\\Apidoc\\src\\jobs\\packlistScheduler.js:312:8)\n    at async PacklistScheduler.processPendingPacklists (C:\\Users\\Administrador.LOAD\\Desktop\\apidoc\\Apidoc\\src\\jobs\\packlistScheduler.js:138:26)\n    at async cron.schedule.timezone (C:\\Users\\Administrador.LOAD\\Desktop\\apidoc\\Apidoc\\src\\jobs\\packlistScheduler.js:47:7)\n    at async Timeout._onTimeout (C:\\Users\\Administrador.LOAD\\Desktop\\apidoc\\Apidoc\\node_modules\\node-cron\\dist\\cjs\\scheduler\\runner.js:70:44)",
  "timestamp": "11/2/2026, 8:28:06 a.m.",
  "data": {
    "packlistId": 1181939,
    "Json": "{\"IdGpoPedidos\":1181939,\"CarrierServices\":\"DHL\",\"ServiceLevel\":\"NBD\",\"ShipmentNumber\":\"EBQ000007389\",\"Customer\":\"Centro de servicio San Pedro Sula\",\"ETA\":\"2026-02-11\",\"priorityName\":\"JD-Normal\",\"shipFrom\":\"{\\\"address\\\":\\\"Poniente 140 Numero 671-A, Col. Industrial Vallejo Azcapotzalco Mexico City, 02300, Mexico\\\",\\\"dayPhone\\\":\\\"+52 (55) 1672-3160 Ext.601\\\",\\\"eveningPhone\\\":\\\"\\\",\\\"mobilePhone\\\":\\\"+52 (55) 6960-6765\\\",\\\"contactName\\\":\\\"Salvador Gayoso\\\"}\",\"shipTo\":\"{\\\"address\\\":\\\"Bo Guamilito 6 Cal... [TRUNCATED]"
  },
  "schedulerInfo": {
    "processedIds": [
      1181863,
      1181865,
      1181864,
      1181866,
      1181736,
      1181869,
      1181870,
      1181871,
      1181872,
      1181873
    ],
    "retryCount": 0,
    "lastProcessed": "2026-02-11T05:02:07.475Z"
  }
}